Metadata-Version: 2.1
Name: plombery-multidb
Version: 0.4.1
Summary: Python task scheduler with a user-friendly web UI
Author-email: Samuel Samson <sam@108capital.ltd>, Luca Faggianelli <luca@velvetlab.tech>
License: MIT
Keywords: pipeline,task-scheduler,apscheduler,orchestrator,web-ui,fastapi,pydantic
Classifier: Programming Language :: Python :: 3
Requires-Python: >=3.8
License-File: LICENSE
Requires-Dist: APScheduler ==3.10.4
Requires-Dist: apprise ==1.6.0
Requires-Dist: authlib ==1.2.1
Requires-Dist: fastapi ==0.104.0
Requires-Dist: httpx ==0.25.0
Requires-Dist: itsdangerous ==2.1.2
Requires-Dist: jinja2 ==3.1.2
Requires-Dist: pydantic ==2.4.2
Requires-Dist: pydantic-settings ==2.0.3
Requires-Dist: python-socketio <6.0.0,>=5.0.0
Requires-Dist: python-dotenv ==1.0.0
Requires-Dist: SQLAlchemy ==2.0.22
Requires-Dist: uvicorn ==0.23.2
Provides-Extra: dev
Requires-Dist: black ==23.10.1 ; extra == 'dev'
Requires-Dist: coverage ==7.3.2 ; extra == 'dev'
Requires-Dist: flake8 ==6.1.0 ; extra == 'dev'
Requires-Dist: pytest ==7.4.3 ; extra == 'dev'
Requires-Dist: pytest-asyncio ==0.21.1 ; extra == 'dev'
Requires-Dist: pytest-env ==1.1.0 ; extra == 'dev'
Provides-Extra: docs
Requires-Dist: mkdocs-material <9.5,>=9.1 ; extra == 'docs'
